odoo/addons/grupxarxa/__init__.py
odoo/addons/grupxarxa/__manifest__.py
odoo/addons/grupxarxa/views/account_views.xml
odoo_addon_grupxarxa-16.0.0.1.0.dist-info/METADATA
odoo_addon_grupxarxa-16.0.0.1.0.dist-info/WHEEL
odoo_addon_grupxarxa-16.0.0.1.0.dist-info/top_level.txt
odoo_addon_grupxarxa-16.0.0.1.0.dist-info/RECORD
