Metadata-Version: 2.1
Name: odoo-addon-grupxarxa
Version: 16.0.0.1.0
Requires-Python: >=3.10
Requires-Dist: odoo-addon-account_move_fiscal_year>=16.0dev,<16.1dev
Requires-Dist: odoo>=16.0a,<16.1dev
Summary: Odoo customization for Grup Xarxa
Home-page: https://git.coopdevs.org/coopdevs/odoo/odoo-addons/odoo-grupxarxa
Author: Coopdevs
Classifier: Programming Language :: Python
Classifier: Framework :: Odoo
Classifier: Framework :: Odoo :: 16.0
